step_functions_sandbox_client/__init__.py
step_functions_sandbox_client/a_thrown_exception.py
step_functions_sandbox_client/aws_resource_driver.py
step_functions_sandbox_client/aws_resource_mocking_engine.py
step_functions_sandbox_client/aws_test_double_driver.py
step_functions_sandbox_client/boto_session_factory.py
step_functions_sandbox_client/cloudformation_stack.py
step_functions_sandbox_client/lambda_function_event_listener.py
step_functions_sandbox_client/s3_bucket.py
step_functions_sandbox_client/state_machine.py
step_functions_sandbox_client/test_resources_factory.py
step_functions_sandbox_client-0.1.2a8.dist-info/METADATA
step_functions_sandbox_client-0.1.2a8.dist-info/WHEEL
step_functions_sandbox_client-0.1.2a8.dist-info/RECORD
