Metadata-Version: 2.3
Name: step-functions-sandbox-client
Version: 0.1.2a8
Summary: Add your description here
Requires-Python: >=3.8
Requires-Dist: boto3-stubs[cloudformation,s3,sqs,stepfunctions,sts]>=1.29.7
Requires-Dist: boto3>=1.29.7
